{
  "post_id": "3790359758679116015",
  "post_shortcode": "DSaEB5LAQjv",
  "likes": 66,
  "liked": false,
  "pinned": [],
  "description": "Our Symbol 👁️\n\nNot Red’s logo is the quiet assurance that you are protected and powerful, even when the world feels chaotic. \n\nWe believe protection is a luxury, which is why the Eye of Horus sits at the heart of our brand: a silent guardian hidden within our logo and every piece we create.\n\n#notred #red #eyeofhorus #ai #design",
  "tags": [
    "#ai",
    "#design",
    "#eyeofhorus",
    "#notred",
    "#red"
  ],
  "location_id": "106377336067638",
  "location_slug": "bangalore",
  "location_url": "https://www.instagram.com/explore/locations/106377336067638/bangalore/",
  "coauthors": [
    {
      "id": "7481838504",
      "username": "phaserbeats_",
      "full_name": "akash | producer/beatmaker"
    },
    {
      "id": "75580543485",
      "username": "notredindia",
      "full_name": "Not Red"
    }
  ],
  "sidecar_media_id": "3790359758679116015",
  "sidecar_shortcode": "DSaEB5LAQjv",
  "owner_id": "8045543808",
  "username": "siddhii.sawant_",
  "fullname": "siddhi | Illustrator",
  "post_date": "2025-12-18 13:55:15",
  "date": "2025-12-18 13:55:14",
  "audio_title": "Lychee Martini",
  "audio_duration": 121.907,
  "audio_user": {
    "pk": "350506587",
    "pk_id": "350506587",
    "id": "350506587",
    "username": "lithe",
    "full_name": "Lithe",
    "is_private": false,
    "is_verified": true,
    "profile_pic_id": "3762631199165708244_350506587",
    "profile_pic_url": "https://instagram.fblr22-1.fna.fbcdn.net/v/t51.82787-19/576083881_18539754223042588_4121383352971130145_n.jpg?stp=dst-jpg_s150x150_tt6&efg=eyJ2ZW5jb2RlX3RhZyI6InByb2ZpbGVfcGljLmRqYW5nby4xMDgwLmMyIn0&_nc_ht=instagram.fblr22-1.fna.fbcdn.net&_nc_cat=104&_nc_oc=Q6cZ2gFxEHly1W99A0nK8P7GCdGJPe8PYaiPx4UN9bpBwH7ENAKRk6IjyN0XkKgS4R06kMNQ-M_Q7bqhfmaSjqWZwzw5&_nc_ohc=T_PnjZOm6LQQ7kNvwE2_7Ml&_nc_gid=SG68IIFW8R2AJgxqXvWbXQ&edm=ABmJApABAAAA&ccb=7-5&oh=00_Af-NVhwH3-cj59neUXr_DfaXAOl3v7QfRDX6eQYM4MsMIQ&oe=6A3ADBE1&_nc_sid=b41fef",
    "strong_id__": "350506587"
  },
  "audio_artist": "Lithe",
  "audio_timestamps": [
    6000,
    21000,
    36000
  ],
  "type": "post",
  "post_url": "https://www.instagram.com/p/DSaEB5LAQjv/",
  "user": {
    "fbid_v2": "17841475584577567",
    "pk": "75580543485",
    "pk_id": "75580543485",
    "is_verified_search_boosted": false,
    "third_party_downloads_enabled": 1,
    "strong_id__": "75580543485",
    "id": "75580543485",
    "full_name": "Not Red",
    "is_private": false,
    "is_verified": true,
    "profile_pic_id": "3773754200401338264_75580543485",
    "profile_pic_url": "https://instagram.fblr22-1.fna.fbcdn.net/v/t51.82787-19/587916381_17863820739519486_5583994406862742068_n.jpg?stp=dst-jpg_s150x150_tt6&efg=eyJ2ZW5jb2RlX3RhZyI6InByb2ZpbGVfcGljLmRqYW5nby4xMDgwLmMyIn0&_nc_ht=instagram.fblr22-1.fna.fbcdn.net&_nc_cat=106&_nc_oc=Q6cZ2gHa-7cRkWEwd4zXkbW413FJI5moKhcu-6taYnBMwsON0vSvz6OkX1IFB_ad54JW0TtgnXH38vr-3J4eKA_Uw9sO&_nc_ohc=26cbqOvdtW8Q7kNvwFAPzoJ&_nc_gid=WWBem1YaxFbEF622g2lroQ&edm=AHG7ALcBAAAA&ccb=7-5&oh=00_Af-2tT819rmDtLpXjmbrTYbzoU1JPAfOEiy_RJjaTasm5g&oe=6A3AB4C7&_nc_sid=c9086e",
    "username": "notredindia",
    "account_badges": [],
    "friendship_status": {
      "following": false,
      "is_bestie": false,
      "is_feed_favorite": false,
      "is_private": false,
      "is_restricted": false,
      "incoming_request": false,
      "outgoing_request": false
    },
    "has_anonymous_profile_picture": false,
    "is_ring_creator": false,
    "latest_reel_media": 1781784968,
    "should_show_category": false,
    "show_ig_app_switcher_badge": true,
    "show_ring_award": false,
    "show_text_post_app_badge": true,
    "unseen_count": 0,
    "search_social_context_snippet_type": "typeahead_follow_count",
    "count_media": 0,
    "count_video": 0,
    "count_saved": 0,
    "count_mutual": 0,
    "count_follow": 0,
    "count_followed": 0,
    "count_collection": 0
  },
  "count": 4,
  "category": "instagram",
  "subcategory": "posts",
  "num": 1,
  "media_id": "3790359749904663707",
  "shortcode": "DSaEBxAAYSb",
  "display_url": "https://instagram.fblr22-2.fna.fbcdn.net/v/t51.82787-15/598150351_18310958806271809_2653324651997081601_n.jpg?stp=dst-jpg_e35_tt6&_nc_cat=110&ig_cache_key=Mzc5MDM1OTc0OTkwNDY2MzcwNw%3D%3D.3-ccb7-5&ccb=7-5&_nc_sid=58cdad&efg=eyJ2ZW5jb2RlX3RhZyI6IkNBUk9VU0VMX0lURU0ueHBpZHMuMTA4MC5zZHIucmVndWxhcl9waG90by5DMyJ9&_nc_ohc=byt_IF5xhWcQ7kNvwF1vfrb&_nc_oc=AdpbCih3569aE39FYubD_CBSw1tZEKieriK5qJ8426og3kwZp62JgwY7qgiWzGMVqMdFSo9kfiJTDohLvsHdaugj&_nc_ad=z-m&_nc_cid=0&_nc_zt=23&_nc_ht=instagram.fblr22-2.fna&_nc_gid=SG68IIFW8R2AJgxqXvWbXQ&_nc_ss=7a22e&oh=00_Af8Y6HTbwTPNA6WY3iuaxrxU1CGj3ao7WPfZZSjvQ4wwRg&oe=6A3AAA40",
  "video_url": null,
  "width": 1080,
  "width_original": 1080,
  "height": 1350,
  "height_original": 1350,
  "tagged_users": [
    {
      "id": "7481838504",
      "username": "phaserbeats_",
      "full_name": "akash | producer/beatmaker"
    },
    {
      "id": "75580543485",
      "username": "notredindia",
      "full_name": "Not Red"
    }
  ],
  "filename": "598150351_18310958806271809_2653324651997081601_n",
  "extension": "jpg",
  "visual_description": {
    "subject": "A red-lit snake with mouth open wide set against a black background, overlaid with the NOT RED logo combining letterforms with the Eye of Horus",
    "composition": "Snake occupies the lower-right quadrant facing left while the white logo is centred-left, creating a diagonal tension across the frame",
    "palette": "black, deep crimson, white",
    "lighting": "dramatic low-key red side-light from the right",
    "materials_visible": "none",
    "human_presence": "none",
    "mood": "predatory and mythic",
    "format_signal": "other"
  }
}